petpetgif/__init__.py
petpetgif/petpet.py
petpetgif/saveGif.py
petpetgif/img/pet0.gif
petpetgif/img/pet1.gif
petpetgif/img/pet2.gif
petpetgif/img/pet3.gif
petpetgif/img/pet4.gif
petpetgif/img/pet5.gif
petpetgif/img/pet6.gif
petpetgif/img/pet7.gif
petpetgif/img/pet8.gif
petpetgif/img/pet9.gif
pet_pet_gif-1.0.1.dist-info/LICENSE
pet_pet_gif-1.0.1.dist-info/METADATA
pet_pet_gif-1.0.1.dist-info/WHEEL
pet_pet_gif-1.0.1.dist-info/top_level.txt
pet_pet_gif-1.0.1.dist-info/RECORD
