Metadata-Version: 2.1
Name: pet-pet-gif
Version: 1.0.1
Summary: Generate a petting gif from a static image (known as "petpet", "Pet the X", or "PETTHE").
Home-page: https://github.com/camprevail/pet-pet-gif
Author: camprevail
Author-email: cam.anderson573@gmail.com
License: MIT
Keywords: petpet,petthe,gif
Platform: UNKNOWN
Classifier: Programming Language :: Python :: 3
Classifier: License :: OSI Approved :: MIT License
Classifier: Operating System :: OS Independent
License-File: LICENSE
Requires-Dist: pillow
Requires-Dist: setuptools
